thonnycontrib/grader101/__init__.py
thonny_grader101-1.1.5.dist-info/METADATA
thonny_grader101-1.1.5.dist-info/WHEEL
thonny_grader101-1.1.5.dist-info/top_level.txt
thonny_grader101-1.1.5.dist-info/RECORD
