Metadata-Version: 2.1
Name: thonny-grader101
Version: 1.1.5
Summary: Thonny Plugins for Grader 101
Home-page: https://2110101.cp.eng.chula.ac.th
Author: somchai.p
Author-email: somchai.p@chula.ac.th
License: MIT
Keywords: Grader101
Platform: Windows
Platform: macOS
Platform: Linux
Classifier: Programming Language :: Python :: 3
Classifier: License :: OSI Approved :: MIT License
Classifier: Operating System :: OS Independent
Requires-Python: >=3.8
Requires-Dist: thonny>=3.0.0
Requires-Dist: requests>=2.27.1
Requires-Dist: bs4>=0.0.2
Requires-Dist: pypdf>=5.4.0
Requires-Dist: m2r2>=0.3.3
